{
  "groups": [
    {
      "name": "camel.component.whatsapp",
      "type": "org.apache.camel.component.whatsapp.springboot.WhatsAppComponentConfiguration",
      "sourceType": "org.apache.camel.component.whatsapp.springboot.WhatsAppComponentConfiguration"
    },
    {
      "name": "camel.component.whatsapp.customizer",
      "type": "org.apache.camel.spring.boot.ComponentConfigurationPropertiesCommon$CustomizerProperties",
      "sourceType": "org.apache.camel.component.whatsapp.springboot.WhatsAppComponentConfiguration",
      "sourceMethod": "getCustomizer()"
    }
  ],
  "properties": [
    {
      "name": "camel.component.whatsapp.api-version",
      "type": "java.lang.String",
      "description": "WhatsApp Cloud API version",
      "sourceType": "org.apache.camel.component.whatsapp.springboot.WhatsAppComponentConfiguration",
      "defaultValue": "v13.0"
    },
    {
      "name": "camel.component.whatsapp.authorization-token",
      "type": "java.lang.String",
      "description": "Authorization Token taken from WhatsApp Meta for Developers Dashboard",
      "sourceType": "org.apache.camel.component.whatsapp.springboot.WhatsAppComponentConfiguration"
    },
    {
      "name": "camel.component.whatsapp.autowired-enabled",
      "type": "java.lang.Boolean",
      "description": "Whether autowiring is enabled. This is used for automatic autowiring options (the option must be marked as autowired) by looking up in the registry to find if there is a single instance of matching type, which then gets configured on the component. This can be used for automatic configuring JDBC data sources, JMS connection factories, AWS Clients, etc.",
      "sourceType": "org.apache.camel.component.whatsapp.springboot.WhatsAppComponentConfiguration",
      "defaultValue": true
    },
    {
      "name": "camel.component.whatsapp.base-uri",
      "type": "java.lang.String",
      "description": "Can be used to set an alternative base URI, e.g. when you want to test the component against a mock WhatsApp API",
      "sourceType": "org.apache.camel.component.whatsapp.springboot.WhatsAppComponentConfiguration",
      "defaultValue": "https:\/\/graph.facebook.com"
    },
    {
      "name": "camel.component.whatsapp.client",
      "type": "java.net.http.HttpClient",
      "description": "Java 11 HttpClient implementation. The option is a java.net.http.HttpClient type.",
      "sourceType": "org.apache.camel.component.whatsapp.springboot.WhatsAppComponentConfiguration"
    },
    {
      "name": "camel.component.whatsapp.customizer.enabled",
      "type": "java.lang.Boolean",
      "sourceType": "org.apache.camel.spring.boot.ComponentConfigurationPropertiesCommon$CustomizerProperties"
    },
    {
      "name": "camel.component.whatsapp.enabled",
      "type": "java.lang.Boolean",
      "description": "Whether to enable auto configuration of the whatsapp component. This is enabled by default.",
      "sourceType": "org.apache.camel.component.whatsapp.springboot.WhatsAppComponentConfiguration"
    },
    {
      "name": "camel.component.whatsapp.lazy-start-producer",
      "type": "java.lang.Boolean",
      "description": "Whether the producer should be started lazy (on the first message). By starting lazy you can use this to allow CamelContext and routes to startup in situations where a producer may otherwise fail during starting and cause the route to fail being started. By deferring this startup to be lazy then the startup failure can be handled during routing messages via Camel's routing error handlers. Beware that when the first message is processed then creating and starting the producer may take a little time and prolong the total processing time of the processing.",
      "sourceType": "org.apache.camel.component.whatsapp.springboot.WhatsAppComponentConfiguration",
      "defaultValue": false
    },
    {
      "name": "camel.component.whatsapp.phone-number-id",
      "type": "java.lang.String",
      "description": "Phone Number ID taken from WhatsApp Meta for Developers Dashboard",
      "sourceType": "org.apache.camel.component.whatsapp.springboot.WhatsAppComponentConfiguration"
    },
    {
      "name": "camel.component.whatsapp.webhook-verify-token",
      "type": "java.lang.String",
      "description": "Webhook verify token",
      "sourceType": "org.apache.camel.component.whatsapp.springboot.WhatsAppComponentConfiguration"
    }
  ],
  "hints": []
}